severus/__init__.py
severus/__version__.py
severus/apis.py
severus/ctx.py
severus/datastructures.py
severus/language.py
severus/py.typed
severus/translator.py
severus-1.4.1.dist-info/METADATA
severus-1.4.1.dist-info/WHEEL
severus-1.4.1.dist-info/licenses/LICENSE
severus-1.4.1.dist-info/RECORD
